README.md
setup.cfg
setup.py
few_shots_clf/__init__.py
few_shots_clf.egg-info/PKG-INFO
few_shots_clf.egg-info/SOURCES.txt
few_shots_clf.egg-info/dependency_links.txt
few_shots_clf.egg-info/requires.txt
few_shots_clf.egg-info/top_level.txt
few_shots_clf/fm_classifier/__init__.py
few_shots_clf/fm_classifier/constants.py
few_shots_clf/fm_classifier/fm_classifier.py
few_shots_clf/fm_classifier/utils/__init__.py
few_shots_clf/fm_classifier/utils/compute_fingerprint.py
few_shots_clf/triplet_classifier/__init__.py
few_shots_clf/triplet_classifier/constants.py
few_shots_clf/triplet_classifier/triplet_classifier.py
few_shots_clf/triplet_classifier/utils/__init__.py
few_shots_clf/triplet_classifier/utils/augmenter.py
few_shots_clf/triplet_classifier/utils/compute_fingerprint.py
few_shots_clf/triplet_classifier/utils/datagenerator.py
few_shots_clf/triplet_classifier/utils/triplet_loss.py
few_shots_clf/triplet_classifier/utils/triplet_model.py
few_shots_clf/utils/__init__.py
few_shots_clf/utils/compute_catalog_fingerprint.py
few_shots_clf/utils/compute_descriptors.py
few_shots_clf/utils/compute_images2labels.py
few_shots_clf/utils/compute_keypoints.py
few_shots_clf/utils/get_all_images_from_folder.py
few_shots_clf/utils/get_iterator.py
few_shots_clf/utils/get_labels_from_catalog.py
few_shots_clf/utils/read_image.py
tests/__init__.py
tests/test_fm_classifier/__init__.py
tests/test_fm_classifier/test_utils/__init__.py
tests/test_fm_classifier/test_utils/test_compute_fingerprint.py
tests/test_utils/__init__.py
tests/test_utils/test_compute_images2labels.py
tests/test_utils/test_get_all_images_from_folder.py
tests/test_utils/test_get_iterator.py
tests/test_utils/test_get_labels_from_catalog.py
tests/test_utils/test_read_image.py