Metadata-Version: 2.1
Name: few-shots-clf
Version: 1.1.3
Summary: Few Shots Classification Library. Classification task from a small amount of data.
Home-page: https://github.com/delmalih/few-shots-clf
Author: David El Malih
Author-email: da.elmalih@gmail.com
License: MIT
Download-URL: https://github.com/delmalih/few-shots-clf/archive/v_113.tar.gz
Keywords: FEW-SHOTS,CLASSIFICATION,IMAGE,COMPUTER VISION
Platform: UNKNOWN
Classifier: License :: OSI Approved :: MIT License
Classifier: Operating System :: OS Independent
Classifier: Programming Language :: Python :: 3
Classifier: Programming Language :: Python :: 3.6
Requires-Python: >=3.6, <3.7
Provides-Extra: dev
Provides-Extra: docs
